README.md
setup.cfg
setup.py
qudo_quantipy/__init__.py
qudo_quantipy/version.py
qudo_quantipy.egg-info/PKG-INFO
qudo_quantipy.egg-info/SOURCES.txt
qudo_quantipy.egg-info/dependency_links.txt
qudo_quantipy.egg-info/requires.txt
qudo_quantipy.egg-info/top_level.txt
qudo_quantipy/core/__init__.py
qudo_quantipy/core/batch.py
qudo_quantipy/core/cache.py
qudo_quantipy/core/chain.py
qudo_quantipy/core/cluster.py
qudo_quantipy/core/dataset.py
qudo_quantipy/core/link.py
qudo_quantipy/core/options.py
qudo_quantipy/core/rules.py
qudo_quantipy/core/stack.py
qudo_quantipy/core/view.py
qudo_quantipy/core/builds/__init__.py
qudo_quantipy/core/builds/excel/__init__.py
qudo_quantipy/core/builds/excel/excel_painter.py
qudo_quantipy/core/builds/excel/formats/__init__.py
qudo_quantipy/core/builds/excel/formats/xlsx_formats.py
qudo_quantipy/core/builds/powerpoint/__init__.py
qudo_quantipy/core/builds/powerpoint/add_shapes.py
qudo_quantipy/core/builds/powerpoint/helpers.py
qudo_quantipy/core/builds/powerpoint/pptx_painter.py
qudo_quantipy/core/builds/powerpoint/transformations.py
qudo_quantipy/core/builds/powerpoint/visual_editor.py
qudo_quantipy/core/builds/powerpoint/templates/__init__.py
qudo_quantipy/core/helpers/__init__.py
qudo_quantipy/core/helpers/constants.py
qudo_quantipy/core/helpers/functions.py
qudo_quantipy/core/quantify/__init__.py
qudo_quantipy/core/quantify/engine.py
qudo_quantipy/core/srv/__init__.py
qudo_quantipy/core/srv/core.py
qudo_quantipy/core/srv/handlers.py
qudo_quantipy/core/srv/servers.py
qudo_quantipy/core/tools/__init__.py
qudo_quantipy/core/tools/audit.py
qudo_quantipy/core/tools/qp_decorators.py
qudo_quantipy/core/tools/dp/__init__.py
qudo_quantipy/core/tools/dp/io.py
qudo_quantipy/core/tools/dp/prep.py
qudo_quantipy/core/tools/dp/query.py
qudo_quantipy/core/tools/dp/ascribe/__init__.py
qudo_quantipy/core/tools/dp/ascribe/reader.py
qudo_quantipy/core/tools/dp/confirmit/__init__.py
qudo_quantipy/core/tools/dp/confirmit/api_requests.py
qudo_quantipy/core/tools/dp/confirmit/helpers.py
qudo_quantipy/core/tools/dp/confirmit/languages_file.py
qudo_quantipy/core/tools/dp/confirmit/reader.py
qudo_quantipy/core/tools/dp/confirmit/writer.py
