Metadata-Version: 2.1
Name: qudo-quantipy
Version: 0.1.1
Summary: A reduced and adapted version of quantipy3 package by author Geir Freysson.
Author: Constance Maurer
License: MIT
Classifier: Development Status :: 5 - Production/Stable
Classifier: Intended Audience :: Developers
Classifier: Intended Audience :: Science/Research
Classifier: Topic :: Software Development
Classifier: Topic :: Scientific/Engineering
Classifier: License :: OSI Approved :: MIT License
Classifier: Programming Language :: Python :: 3.9
